[
 {
  "id": 3,
  "imagen": "/img/products/IMG_DEFAULT.svg",
  "imagenFrontal": "/img/products/IMG_DEFAULT.svg",
  "imagenLateralDerecha": "/img/products/IMG_DEFAULT.svg",
  "imagenLateralIzquierda": "/img/products/IMG_DEFAULT.svg",
  "marca": "Marca",
  "nombre": "Nombre del producto",
  "precio": 10000,
  "descuento": 20,
  "descripcion": "Descripcion",
  "cantidad": 10,
  "coloresDisponibles": "Color",
  "categorias": "Guitarras",
  "estado": "masVendido"
 },
 {
  "id": 4,
  "imagen": "/img/products/IMG_DEFAULT.svg",
  "imagenFrontal": "/img/products/IMG_DEFAULT.svg",
  "imagenLateralDerecha": "/img/products/IMG_DEFAULT.svg",
  "imagenLateralIzquierda": "/img/products/IMG_DEFAULT.svg",
  "marca": "Marca",
  "nombre": "Nombre del producto",
  "precio": 1000,
  "descuento": 20,
  "descripcion": "Descripcion",
  "cantidad": 10,
  "coloresDisponibles": "Color",
  "categorias": "Guitarras",
  "estado": "masVendido"
 },
 {
  "id": 5,
  "imagen": "/img/products/IMG_DEFAULT.svg",
  "imagenFrontal": "/img/products/IMG_DEFAULT.svg",
  "imagenLateralDerecha": "/img/products/IMG_DEFAULT.svg",
  "imagenLateralIzquierda": "/img/products/IMG_DEFAULT.svg",
  "marca": "Marca",
  "nombre": "Nombre del producto",
  "precio": 1000,
  "descuento": 20,
  "descripcion": "Descripcion",
  "cantidad": 10,
  "coloresDisponibles": "Color",
  "categorias": "Guitarras",
  "estado": "masVendido"
 },
 {
  "id": 6,
  "nombre": "dwada",
  "marca": "1421",
  "precio": "212112",
  "descuento": "20",
  "descripcion": "dawdadadad"
 }
]